unja/__init__.py
unja/__main__.py
unja/config.json
unja-0.0.7.dist-info/LICENSE
unja-0.0.7.dist-info/METADATA
unja-0.0.7.dist-info/WHEEL
unja-0.0.7.dist-info/entry_points.txt
unja-0.0.7.dist-info/top_level.txt
unja-0.0.7.dist-info/RECORD
