Metadata-Version: 2.1
Name: unja
Version: 0.0.7
Summary: Fetch Known Urls
Home-page: https://github.com/ninjhacks/unja
Author: Sheryar
Author-email: ninjhacks@protonmail.com
License: GNU General Public License v3 (GPLv3)
Download-URL: https://github.com/ninjhacks/unja/archive/v0.0.7.zip
Keywords: unja,bug bounty,wayback,common crawl,virus total,urlscan,pentesting,recon
Platform: UNKNOWN
Classifier: Development Status :: 5 - Production/Stable
Classifier: Intended Audience :: Developers
Classifier: Intended Audience :: Information Technology
Classifier: Operating System :: OS Independent
Classifier: Topic :: Security
Classifier: License :: OSI Approved :: GNU General Public License v3 (GPLv3)
Classifier: Programming Language :: Python :: 3
Requires-Python: >=3
License-File: LICENSE
Requires-Dist: requests
